nickpkg/__init__.py
nickpkg/add.py
nickpkg-0.1.dist-info/LICENSE
nickpkg-0.1.dist-info/METADATA
nickpkg-0.1.dist-info/WHEEL
nickpkg-0.1.dist-info/top_level.txt
nickpkg-0.1.dist-info/RECORD
