Metadata-Version: 2.1
Name: nickpkg
Version: 0.1
Summary: A simple package to add two numbers
Home-page: https://github.com/yourusername/nickpkg
Author: loujiajia
Author-email: loujiajia1@163.com
Classifier: Programming Language :: Python :: 3
Classifier: License :: OSI Approved :: MIT License
Classifier: Operating System :: OS Independent
Requires-Python: >=3.6
License-File: LICENSE
